k8s_secretgenerator/__init__.py
k8s_secretgenerator/k8s_secret_creator.py
tests/__init__.py
k8s_secretgenerator-1.0.5.dist-info/METADATA
k8s_secretgenerator-1.0.5.dist-info/WHEEL
k8s_secretgenerator-1.0.5.dist-info/top_level.txt
k8s_secretgenerator-1.0.5.dist-info/RECORD
