Metadata-Version: 2.1
Name: k8s-secretgenerator
Version: 1.0.5
Summary: UNKNOWN
Home-page: https://github.com/baspenny/k8s_secretgenerator
License: UNKNOWN
Platform: UNKNOWN
Requires-Python: >=3.7
Requires-Dist: PyYAML
